hti_index/__init__.py
hti_index/component.py
hti_index/composite.py
hti_index/flowfreq.py
hti_index/indexer.py
hti_index/utils.py
hti_index-0.1.2.dist-info/LICENSE
hti_index-0.1.2.dist-info/METADATA
hti_index-0.1.2.dist-info/WHEEL
hti_index-0.1.2.dist-info/top_level.txt
hti_index-0.1.2.dist-info/RECORD
