Metadata-Version: 2.1
Name: hti-index
Version: 0.1.2
Summary: Python package for implementing a HasH Table Index
Home-page: https://github.com/diomandeee/hti_index
Author: Mohamed Diomande
Author-email: gdiomande7907@gmail.com
License: MIT
Classifier: Programming Language :: Python :: 3
Classifier: License :: OSI Approved :: MIT License
Classifier: Operating System :: OS Independent
Requires-Python: >=3.6
License-File: LICENSE
Requires-Dist: numpy
